<?xml version="1.0"?>
<?xml-stylesheet type="text/xsl" href="restaurant.xsl"?>

<root>
<item>
<ID>1</ID>
<feature>
<name>麻辣蜗牛</name>
<domestic>国内</domestic>
<region>川菜</region>
<type>菜品</type>
<favor>鲜</favor>
<favor>麻辣</favor>
<material>蜗牛</material>
<material>鲜花椒</material>
<material>辣椒</material>
</feature>
<owner>
<restaurant>麻辣诱惑（中关村店）</restaurant>
<location>北京市海淀区中关村大街19号新中关2层</location>
<howtoarrive>出北大东门向南直走过海淀大桥向西走，到中关村大街想南走200米右侧2层</howtoarrive>
<price>88</price>
<size>2</size>
<match>酸梅汤</match>
<score>7</score>
<critique>又麻又辣，很好吃</critique>
<connection>水煮鱼</connection>
<connection>香辣盆盆虾</connection>
</owner>
<pic>1.jpg</pic>
</item>

<item>
<ID>2</ID>
<feature>
<name>飘香牛肉</name>
<domestic>国内</domestic>
<region>川菜</region>
<type>菜品</type>
<favor>嫩</favor>
<favor>麻辣</favor>
<material>牛肉</material>
<material>金针菇</material>
<material>辣椒</material>
<material>姜</material>
<material>葱</material>
<material>蒜</material>
</feature>
<owner>
<restaurant>麻辣诱惑（中关村店）</restaurant>
<location>北京市海淀区中关村大街19号新中关2层</location>
<howtoarrive>出北大东门向南直走过海淀大桥向西走，到中关村大街想南走200米右侧2层</howtoarrive>
<price>49</price>
<size>4</size>
<match>酸梅汤</match>
<score>6</score>
<critique>感觉揉了过多的粉，太嫩，然后肉很少，下面都是金针菇</critique>
<connection>水煮鱼</connection>
<connection>上汤娃娃菜</connection>
</owner>
<pic>2.jpg</pic>
</item>

<item>
<ID>3</ID>
<feature>
<name>蓝莓山药</name>
<domestic>国内</domestic>
<region>其他</region>
<type>甜点</type>
<favor>酸甜</favor>
<material>蓝莓</material>
<material>山药</material>
<material>冰糖</material>
<material>奶油</material>
</feature>
<owner>
<restaurant>麻辣诱惑（中关村店）</restaurant>
<location>北京市海淀区中关村大街19号新中关2层</location>
<howtoarrive>出北大东门向南直走过海淀大桥向西走，到中关村大街想南走200米右侧2层</howtoarrive>
<price>22</price>
<size>2</size>
<match>香辣盆盆虾</match>
<score>7</score>
<critique>比较解辣，但感觉没什么特别的</critique>
<connection>麻辣诱惑蛙</connection>
</owner>
<pic>3.jpg</pic>
</item>

<item>
<ID>4</ID>
<feature>
<name>水煮鱼</name>
<domestic>国内</domestic>
<region>川菜</region>
<type>菜品</type>
<favor>麻辣</favor>
<material>草鱼</material>
<material>黄豆芽</material>
<material>干辣椒</material>
<material>花椒</material>
<material>葱</material>
<material>蒜</material>
<material>姜</material>
</feature>
<owner>
<restaurant>麻辣诱惑（中关村店）</restaurant>
<location>北京市海淀区中关村大街19号新中关2层</location>
<howtoarrive>出北大东门向南直走过海淀大桥向西走，到中关村大街想南走200米右侧2层</howtoarrive>
<price>150</price>
<size>3</size>
<match>酸梅汤</match>
<score>8</score>
<critique>香辣，就是有点油腻</critique>
<connection>干锅千叶豆腐</connection>
<connection>麻辣龙虾</connection>
</owner>
<pic>4.jpg</pic>
</item>

<item>
<ID>5</ID>
<feature>
<name>小米椒爱上小公鸡</name>
<domestic>国内</domestic>
<region>川菜</region>
<type>菜品</type>
<favor>麻辣</favor>
<material>鸡腿</material>
<material>米椒</material>
<material>花生</material>
<material>香芹</material>
<material>洋葱</material>
<material>蒜</material>
<material>姜</material>
</feature>
<owner>
<restaurant>麻辣诱惑（中关村店）</restaurant>
<location>北京市海淀区中关村大街19号新中关2层</location>
<howtoarrive>出北大东门向南直走过海淀大桥向西走，到中关村大街想南走200米右侧2层</howtoarrive>
<price>48</price>
<size>3</size>
<match>酸梅汤</match>
<score>8</score>
<critique>评价：这道菜鸡肉嫩滑，里面有麻油的香味，还有淡淡的蒜香味</critique>
<connection>蟹黄豆腐</connection>
<connection>蓝莓山药</connection>
</owner>
<pic>5.jpg</pic>
</item>

<item>
<ID>14</ID>
<feature>
<name>白灼菜心</name>
<domestic>国内</domestic>
<region>粤菜</region>
<type>菜品</type>
<favor>咸</favor>
<favor>脆</favor>
<favor>嫩</favor>
<material>油菜苔</material>
<material>蒜</material>
</feature>
<owner>
<restaurant>麻辣诱惑（中关村店）</restaurant>
<location>北京市海淀区中关村大街19号新中关2层</location>
<howtoarrive>出北大东门向南直走过海淀大桥向西走，到中关村大街想南走200米右侧2层</howtoarrive>
<price>22</price>
<size>2</size>
<match>酸梅汤</match>
<score>6</score>
<critique>没什么特点，但是对于吃了很多辣的我们，还是很清热解辣的</critique>
<connection>面包诱惑</connection>
<connection>上汤蜂窝豆腐</connection>
</owner>
<pic>14.jpg</pic>
</item>

<item>
<ID>15</ID>
<feature>
<name>面包诱惑</name>
<domestic>国内</domestic>
<region>川菜</region>
<type>菜品</type>
<favor>甜</favor>
<favor>滑</favor>
<material>吐司</material>
<material>香草冰激凌</material>
</feature>
<owner>
<restaurant>麻辣诱惑（中关村店）</restaurant>
<location>北京市海淀区中关村大街19号新中关2层</location>
<howtoarrive>出北大东门向南直走过海淀大桥向西走，到中关村大街想南走200米右侧2层</howtoarrive>
<price>38</price>
<size>2</size>
<match>酸梅汤</match>
<score>8</score>
<critique>真的很好吃，面包很焦，冰激凌很甜，很好吃</critique>
<connection>水煮鱼</connection>
<connection>上汤蜂窝豆腐</connection>
</owner>
<pic>15.jpg</pic>
</item>

<item>
<ID>16</ID>
<feature>
<name>上汤蜂窝豆腐</name>
<domestic>国内</domestic>
<region>川菜</region>
<type>菜品</type>
<favor>咸</favor>
<favor>滑</favor>
<favor>嫩</favor>
<material>豆腐</material>
<material>海米</material>
<material>高汤</material>
</feature>
<owner>
<restaurant>麻辣诱惑（中关村店）</restaurant>
<location>北京市海淀区中关村大街19号新中关2层</location>
<howtoarrive>出北大东门向南直走过海淀大桥向西走，到中关村大街想南走200米右侧2层</howtoarrive>
<price>32</price>
<size>3</size>
<match>酸梅汤</match>
<score>7</score>
<critique>解辣，健康，口感好。高汤很鲜美，但是偏咸了</critique>
<connection>面包诱惑</connection>
<connection>上汤菠菜</connection>
</owner>
<pic>16.jpg</pic>
</item>

<item>
<ID>17</ID>
<feature>
<name>粉蒸排骨</name>
<domestic>国内</domestic>
<region>川菜</region>
<type>菜品</type>
<favor>咸</favor>
<favor>软</favor>
<favor>香</favor>
<material>猪小排</material>
<material>土豆</material>
<material>糯米</material>
<material>葱</material>
</feature>
<owner>
<restaurant>麻辣诱惑（中关村店）</restaurant>
<location>北京市海淀区中关村大街19号新中关2层</location>
<howtoarrive>出北大东门向南直走过海淀大桥向西走，到中关村大街想南走200米右侧2层</howtoarrive>
<price>38</price>
<size>3</size>
<match>酸梅汤</match>
<score>6</score>
<critique>感觉没什么特色，这个菜也不是很热好像不是新做出来的，除了咸没什么特别的味道了</critique>
<connection>水煮鱼</connection>
<connection>麻辣诱惑蛙</connection>
</owner>
<pic>17.jpg</pic>
</item>

<item>
<ID>18</ID>
<feature>
<name>麻辣诱惑蛙</name>
<domestic>国内</domestic>
<region>川菜</region>
<type>菜品</type>
<favor>麻辣</favor>
<material>山蛙</material>
<material>丝瓜</material>
<material>香菇</material>
<material>方竹笋</material>
<material>辣椒</material>
</feature>
<owner>
<restaurant>麻辣诱惑（中关村店）</restaurant>
<location>北京市海淀区中关村大街19号新中关2层</location>
<howtoarrive>出北大东门向南直走过海淀大桥向西走，到中关村大街想南走200米右侧2层</howtoarrive>
<price>59</price>
<size>3</size>
<match>酸梅汤</match>
<score>7</score>
<critique>实在是没有看到什么蛙，感觉大多数都是菜，也不够辣，油腻</critique>
<connection>水煮鱼</connection>
<connection>毛血旺</connection>
</owner>
<pic>18.jpg</pic>
</item>

<item>
<ID>19</ID>
<feature>
<name>香辣盆盆虾</name>
<domestic>国内</domestic>
<region>川菜</region>
<type>菜品</type>
<favor>麻辣</favor>
<material>白虾</material>
<material>芹菜段</material>
<material>香菇</material>
<material>方竹笋</material>
<material>辣椒</material>
<material>葱段</material>
</feature>
<owner>
<restaurant>麻辣诱惑（中关村店）</restaurant>
<location>北京市海淀区中关村大街19号新中关2层</location>
<howtoarrive>出北大东门向南直走过海淀大桥向西走，到中关村大街想南走200米右侧2层</howtoarrive>
<price>53</price>
<size>3</size>
<match>酸梅汤</match>
<score>8</score>
<critique>香辣味，肉厚色鲜，香辣味美，吃了让人欲罢不能，但可能对于不太能吃辣的人来说过于辣</critique>
<connection>水煮鱼</connection>
<connection>蟹黄豆腐</connection>
</owner>
<pic>19.jpg</pic>
</item>

<item>
<ID>41</ID>
<feature>
<name>麻辣香锅鸡翅</name>
<domestic>国内</domestic>
<region>川菜</region>
<type>菜品</type>
<favor>香</favor>
<favor>特辣</favor>
<material>鸡肉</material>
<material>土豆</material>
<material>莴笋</material>
<material>藕</material>
</feature>
<owner>
<restaurant>麻辣诱惑</restaurant>
<location>北京市海淀区中关村大街15号津乐汇购物广场二层</location>
<howtoarrive>以北大南门为起点，像正东走约100米右转，再走约100米左转，直行过海淀桥后走至上品折扣，在路口左转，直行过三个红绿灯后见津乐汇，直上二楼</howtoarrive>
<price>56</price>
<size>4</size>
<match>可乐</match>
<score>7</score>
<critique>很不错，辣的爽</critique>
<connection>麻辣香锅牛蛙</connection>
</owner>
<pic>41.jpg</pic>
</item>

<item>
<ID>47</ID>
<feature>
<name>蟹黄豆腐</name>
<domestic>国内</domestic>
<region>其他</region>
<type>菜品</type>
<favor>鲜</favor>
<favor>香</favor>
<favor>滑</favor>
<favor>嫩</favor>
<material>螃蟹</material>
<material>豆腐</material>
<material>鸡蛋</material>
<material>虾仁</material>
</feature>
<owner>
<restaurant>麻辣诱惑</restaurant>
<location>北京市海淀区中关村大街15号津乐汇购物广场二层</location>
<howtoarrive>以北大南门为起点，像正东走约100米右转，再走约100米左转，直行过海淀桥后走至上品折扣，在路口左转，直行过三个红绿灯后见津乐汇，直上二楼</howtoarrive>
<price>36</price>
<size>3</size>
<match>西米露</match>
<score>7</score>
<critique>味道一如既往的好</critique>
<connection>上汤娃娃菜</connection>
</owner>
<pic>47.jpg</pic>
</item>

<item>
<ID>50</ID>
<feature>
<name>毛血旺</name>
<domestic>国内</domestic>
<region>川菜</region>
<type>菜品</type>
<favor>滑</favor>
<favor>香</favor>
<favor>麻辣</favor>
<material>鸭血</material>
<material>牛百叶</material>
<material>莴笋</material>
<material>黑鱼片</material>
<material>辣椒</material>
<material>鳝鱼</material>
</feature>
<owner>
<restaurant>麻辣诱惑</restaurant>
<location>北京市海淀区中关村大街15号津乐汇购物广场二层</location>
<howtoarrive>以北大南门为起点，像正东走约100米右转，再走约100米左转，直行过海淀桥后走至上品折扣，在路口左转，直行过三个红绿灯后见津乐汇，直上二楼</howtoarrive>
<price>47</price>
<size>3</size>
<match>蟹黄豆腐</match>
<score>9</score>
<critique>特别新鲜，吃的很过瘾，每次必点！！</critique>
<connection>麻辣小龙虾</connection>
</owner>
<pic>50.jpg</pic>
</item>


</root>

